{
  "timestamp": "2025-09-09T02:43:09.027Z",
  "reports": [
    {
      "url": "https://jefrydco.id/",
      "device": "mobile",
      "perf": 1,
      "fid": 0,
      "lcp": 780.89,
      "cls": 0.01068,
      "fcp": 780.89,
      "fci": 0,
      "tbt": 20,
      "tti": 1993.17,
      "si": 780.89,
      "req": 22,
      "size": 346420
    },
    {
      "url": "https://jefrydco.id/",
      "device": "desktop",
      "perf": 1,
      "fid": 0,
      "lcp": 260.63,
      "cls": 0.00139,
      "fcp": 260.63,
      "fci": 0,
      "tbt": 31,
      "tti": 499.27,
      "si": 274.22,
      "req": 22,
      "size": 346540
    },
    {
      "url": "https://jefrydco.id/blog/",
      "device": "mobile",
      "perf": 0.84,
      "fid": 0,
      "lcp": 4624.22,
      "cls": 0.02419,
      "fcp": 920.03,
      "fci": 0,
      "tbt": 50,
      "tti": 4706.73,
      "si": 1606.25,
      "req": 26,
      "size": 850753
    },
    {
      "url": "https://jefrydco.id/blog/",
      "device": "desktop",
      "perf": 0.98,
      "fid": 0,
      "lcp": 1047.17,
      "cls": 0.00086,
      "fcp": 374.05,
      "fci": 0,
      "tbt": 6,
      "tti": 1065.07,
      "si": 616.46,
      "req": 27,
      "size": 876201
    },
    {
      "url": "https://jefrydco.id/talk/",
      "device": "mobile",
      "perf": 0.85,
      "fid": 0,
      "lcp": 3977.01,
      "cls": 0.01477,
      "fcp": 2251,
      "fci": 0,
      "tbt": 84,
      "tti": 4044.61,
      "si": 2251,
      "req": 26,
      "size": 828473
    },
    {
      "url": "https://jefrydco.id/talk/",
      "device": "desktop",
      "perf": 0.98,
      "fid": 0,
      "lcp": 1116.03,
      "cls": 0.0004,
      "fcp": 453.01,
      "fci": 0,
      "tbt": 23,
      "tti": 1144.74,
      "si": 533.61,
      "req": 31,
      "size": 1097547
    }
  ]
}