{
  "timestamp": "2026-03-28T02:14:28.181Z",
  "reports": [
    {
      "url": "https://jefrydco.id/",
      "device": "mobile",
      "perf": 0.91,
      "fid": 0,
      "lcp": 3321.93,
      "cls": 0,
      "fcp": 1585.92,
      "fci": 0,
      "tbt": 29,
      "tti": 3329.49,
      "si": 2813.21,
      "req": 17,
      "size": 286537
    },
    {
      "url": "https://jefrydco.id/",
      "device": "desktop",
      "perf": 1,
      "fid": 0,
      "lcp": 419.32,
      "cls": 0.001,
      "fcp": 336.12,
      "fci": 0,
      "tbt": 1,
      "tti": 575.88,
      "si": 364.88,
      "req": 17,
      "size": 286455
    },
    {
      "url": "https://jefrydco.id/blog/",
      "device": "mobile",
      "perf": 0.91,
      "fid": 0,
      "lcp": 3336.76,
      "cls": 0,
      "fcp": 1378.43,
      "fci": 0,
      "tbt": 49,
      "tti": 3344.3,
      "si": 2550.21,
      "req": 16,
      "size": 246367
    },
    {
      "url": "https://jefrydco.id/blog/",
      "device": "desktop",
      "perf": 1,
      "fid": 0,
      "lcp": 784,
      "cls": 0,
      "fcp": 339,
      "fci": 0,
      "tbt": 12,
      "tti": 784,
      "si": 483.79,
      "req": 16,
      "size": 246519
    },
    {
      "url": "https://jefrydco.id/talk/",
      "device": "mobile",
      "perf": 0.89,
      "fid": 0,
      "lcp": 3752,
      "cls": 0,
      "fcp": 1372,
      "fci": 0,
      "tbt": 0,
      "tti": 3782,
      "si": 1419.43,
      "req": 22,
      "size": 1093768
    },
    {
      "url": "https://jefrydco.id/talk/",
      "device": "desktop",
      "perf": 0.97,
      "fid": 0,
      "lcp": 1263,
      "cls": 0.00003,
      "fcp": 335,
      "fci": 0,
      "tbt": 3,
      "tti": 1269,
      "si": 512.45,
      "req": 22,
      "size": 1093747
    }
  ]
}