{
  "timestamp": "2025-04-28T02:52:40.973Z",
  "reports": [
    {
      "url": "https://jefrydco.id/",
      "device": "mobile",
      "perf": 1,
      "fid": 0,
      "lcp": 784.56,
      "cls": 0.01068,
      "fcp": 784.56,
      "fci": 0,
      "tbt": 17.5,
      "tti": 2004.59,
      "si": 951.89,
      "req": 22,
      "size": 344843
    },
    {
      "url": "https://jefrydco.id/",
      "device": "desktop",
      "perf": 1,
      "fid": 0,
      "lcp": 285.48,
      "cls": 0.00134,
      "fcp": 285.48,
      "fci": 0,
      "tbt": 28,
      "tti": 493.17,
      "si": 285.48,
      "req": 22,
      "size": 344920
    },
    {
      "url": "https://jefrydco.id/blog/",
      "device": "mobile",
      "perf": 0.84,
      "fid": 0,
      "lcp": 4540.11,
      "cls": 0.02418,
      "fcp": 937.02,
      "fci": 0,
      "tbt": 61,
      "tti": 4630.11,
      "si": 1715.41,
      "req": 26,
      "size": 847956
    },
    {
      "url": "https://jefrydco.id/blog/",
      "device": "desktop",
      "perf": 0.99,
      "fid": 0,
      "lcp": 1035.07,
      "cls": 0.00056,
      "fcp": 336.02,
      "fci": 0,
      "tbt": 58,
      "tti": 1053.68,
      "si": 506.33,
      "req": 27,
      "size": 872412
    },
    {
      "url": "https://jefrydco.id/talk/",
      "device": "mobile",
      "perf": 0.87,
      "fid": 0,
      "lcp": 3987.26,
      "cls": 0.01477,
      "fcp": 937,
      "fci": 0,
      "tbt": 116.5,
      "tti": 4053.84,
      "si": 1861,
      "req": 26,
      "size": 827215
    },
    {
      "url": "https://jefrydco.id/talk/",
      "device": "desktop",
      "perf": 0.93,
      "fid": 0,
      "lcp": 1187.76,
      "cls": 0.00064,
      "fcp": 481.5,
      "fci": 0,
      "tbt": 178,
      "tti": 1209.34,
      "si": 789.13,
      "req": 31,
      "size": 1097438
    }
  ]
}