{
  "timestamp": "2022-11-05T03:08:06.487Z",
  "reports": [
    {
      "url": "https://jefrydco.id/",
      "device": "mobile",
      "perf": 0.82,
      "fid": 0,
      "lcp": 3492,
      "cls": 0.00107,
      "fcp": 862,
      "fci": 0,
      "tbt": 337.5,
      "tti": 3576,
      "si": 1418.94,
      "req": 24,
      "size": 336937
    },
    {
      "url": "https://jefrydco.id/",
      "device": "desktop",
      "perf": 1,
      "fid": 3,
      "lcp": 788,
      "cls": 0.00138,
      "fcp": 240,
      "fci": 0,
      "tbt": 0,
      "tti": 240,
      "si": 331.08,
      "req": 24,
      "size": 337005
    },
    {
      "url": "https://jefrydco.id/blog/",
      "device": "mobile",
      "perf": 0.57,
      "fid": 0,
      "lcp": 5468,
      "cls": 0.00107,
      "fcp": 1000,
      "fci": 0,
      "tbt": 817.5,
      "tti": 5354,
      "si": 2305.24,
      "req": 27,
      "size": 726136
    },
    {
      "url": "https://jefrydco.id/blog/",
      "device": "desktop",
      "perf": 0.97,
      "fid": 3,
      "lcp": 1305.5,
      "cls": 0.00054,
      "fcp": 324,
      "fci": 0,
      "tbt": 32.5,
      "tti": 1203,
      "si": 468.38,
      "req": 29,
      "size": 863124
    },
    {
      "url": "https://jefrydco.id/talk/",
      "device": "mobile",
      "perf": 0.67,
      "fid": 0,
      "lcp": 4865.5,
      "cls": 0.00107,
      "fcp": 1015,
      "fci": 0,
      "tbt": 541,
      "tti": 3670,
      "si": 2162.19,
      "req": 27,
      "size": 527486
    },
    {
      "url": "https://jefrydco.id/talk/",
      "device": "desktop",
      "perf": 0.96,
      "fid": 3,
      "lcp": 1419,
      "cls": 0.00063,
      "fcp": 443,
      "fci": 0,
      "tbt": 23.5,
      "tti": 795,
      "si": 495.17,
      "req": 33,
      "size": 1088977
    }
  ]
}