{
  "timestamp": "2023-10-30T02:03:02.307Z",
  "reports": [
    {
      "url": "https://jefrydco.id/",
      "device": "mobile",
      "perf": 0.75,
      "fid": 0,
      "lcp": 3661.5,
      "cls": 0.01068,
      "fcp": 922,
      "fci": 0,
      "tbt": 592,
      "tti": 3687.5,
      "si": 922,
      "req": 0,
      "size": 0
    },
    {
      "url": "https://jefrydco.id/",
      "device": "desktop",
      "perf": 0.98,
      "fid": 0,
      "lcp": 1169.25,
      "cls": 0.00134,
      "fcp": 383,
      "fci": 0,
      "tbt": 17,
      "tti": 596.5,
      "si": 415.81,
      "req": 0,
      "size": 0
    },
    {
      "url": "https://jefrydco.id/blog/",
      "device": "mobile",
      "perf": 0.6,
      "fid": 0,
      "lcp": 5490.5,
      "cls": 0.02418,
      "fcp": 1132,
      "fci": 0,
      "tbt": 845.5,
      "tti": 5199.5,
      "si": 2491.37,
      "req": 0,
      "size": 0
    },
    {
      "url": "https://jefrydco.id/blog/",
      "device": "desktop",
      "perf": 0.94,
      "fid": 0,
      "lcp": 1353.5,
      "cls": 0.00054,
      "fcp": 519.5,
      "fci": 0,
      "tbt": 140,
      "tti": 1174,
      "si": 657.13,
      "req": 0,
      "size": 0
    },
    {
      "url": "https://jefrydco.id/talk/",
      "device": "mobile",
      "perf": 0.6,
      "fid": 0,
      "lcp": 4709,
      "cls": 0.01454,
      "fcp": 1911,
      "fci": 0,
      "tbt": 955.5,
      "tti": 3848,
      "si": 2318.81,
      "req": 0,
      "size": 0
    },
    {
      "url": "https://jefrydco.id/talk/",
      "device": "desktop",
      "perf": 0.96,
      "fid": 0,
      "lcp": 1288.5,
      "cls": 0.00063,
      "fcp": 471,
      "fci": 0,
      "tbt": 105,
      "tti": 740,
      "si": 471,
      "req": 0,
      "size": 0
    }
  ]
}