{
  "timestamp": "2023-04-07T02:10:16.028Z",
  "reports": [
    {
      "url": "https://jefrydco.id/",
      "device": "mobile",
      "perf": 0.75,
      "fid": 0,
      "lcp": 4245,
      "cls": 0.01068,
      "fcp": 892,
      "fci": 0,
      "tbt": 424,
      "tti": 3360,
      "si": 892,
      "req": 24,
      "size": 339783
    },
    {
      "url": "https://jefrydco.id/",
      "device": "desktop",
      "perf": 1,
      "fid": 0,
      "lcp": 810,
      "cls": 0.00139,
      "fcp": 361,
      "fci": 0,
      "tbt": 15,
      "tti": 426,
      "si": 361,
      "req": 24,
      "size": 339828
    },
    {
      "url": "https://jefrydco.id/blog/",
      "device": "mobile",
      "perf": 0.63,
      "fid": 0,
      "lcp": 5119,
      "cls": 0.02418,
      "fcp": 1530,
      "fci": 0,
      "tbt": 694,
      "tti": 5040,
      "si": 2628.36,
      "req": 28,
      "size": 842073
    },
    {
      "url": "https://jefrydco.id/blog/",
      "device": "desktop",
      "perf": 0.96,
      "fid": 0,
      "lcp": 1249,
      "cls": 0.00084,
      "fcp": 510,
      "fci": 0,
      "tbt": 92,
      "tti": 697,
      "si": 963.96,
      "req": 29,
      "size": 866319
    },
    {
      "url": "https://jefrydco.id/talk/",
      "device": "mobile",
      "perf": 0.63,
      "fid": 0,
      "lcp": 4759,
      "cls": 0.02133,
      "fcp": 1530,
      "fci": 0,
      "tbt": 775.5,
      "tti": 3757,
      "si": 2788.29,
      "req": 28,
      "size": 821528
    },
    {
      "url": "https://jefrydco.id/talk/",
      "device": "desktop",
      "perf": 0.96,
      "fid": 0,
      "lcp": 1335.5,
      "cls": 0.00063,
      "fcp": 470,
      "fci": 0,
      "tbt": 65,
      "tti": 696,
      "si": 549.35,
      "req": 33,
      "size": 1090651
    }
  ]
}