{
  "timestamp": "2026-03-09T02:14:36.647Z",
  "reports": [
    {
      "url": "https://jefrydco.id/",
      "device": "mobile",
      "perf": 0.92,
      "fid": 0,
      "lcp": 3299.82,
      "cls": 0,
      "fcp": 1588.32,
      "fci": 0,
      "tbt": 3,
      "tti": 3307.38,
      "si": 2805.64,
      "req": 17,
      "size": 289017
    },
    {
      "url": "https://jefrydco.id/",
      "device": "desktop",
      "perf": 1,
      "fid": 0,
      "lcp": 521,
      "cls": 0.001,
      "fcp": 337,
      "fci": 0,
      "tbt": 21,
      "tti": 632,
      "si": 337,
      "req": 17,
      "size": 288972
    },
    {
      "url": "https://jefrydco.id/blog/",
      "device": "mobile",
      "perf": 0.97,
      "fid": 0,
      "lcp": 2404.02,
      "cls": 0.0225,
      "fcp": 1373.51,
      "fci": 0,
      "tbt": 15.5,
      "tti": 2567.64,
      "si": 1373.51,
      "req": 16,
      "size": 248994
    },
    {
      "url": "https://jefrydco.id/blog/",
      "device": "desktop",
      "perf": 1,
      "fid": 0,
      "lcp": 496.38,
      "cls": 0.00103,
      "fcp": 349.63,
      "fci": 0,
      "tbt": 7,
      "tti": 636.26,
      "si": 461.18,
      "req": 16,
      "size": 248977
    },
    {
      "url": "https://jefrydco.id/talk/",
      "device": "mobile",
      "perf": 0.88,
      "fid": 0,
      "lcp": 3977,
      "cls": 0,
      "fcp": 926,
      "fci": 0,
      "tbt": 14,
      "tti": 4059.5,
      "si": 1107.97,
      "req": 22,
      "size": 1096168
    },
    {
      "url": "https://jefrydco.id/talk/",
      "device": "desktop",
      "perf": 0.99,
      "fid": 0,
      "lcp": 1021,
      "cls": 0.00004,
      "fcp": 334,
      "fci": 0,
      "tbt": 21,
      "tti": 1027,
      "si": 429.79,
      "req": 22,
      "size": 1096137
    }
  ]
}