{
  "timestamp": "2026-01-20T02:13:32.311Z",
  "reports": [
    {
      "url": "https://jefrydco.id/",
      "device": "mobile",
      "perf": 0.96,
      "fid": 0,
      "lcp": 2572.91,
      "cls": 0.05889,
      "fcp": 1588.85,
      "fci": 0,
      "tbt": 33,
      "tti": 2572.91,
      "si": 1906.51,
      "req": 17,
      "size": 288234
    },
    {
      "url": "https://jefrydco.id/",
      "device": "desktop",
      "perf": 1,
      "fid": 0,
      "lcp": 401,
      "cls": 0.001,
      "fcp": 333,
      "fci": 0,
      "tbt": 30,
      "tti": 646,
      "si": 333,
      "req": 17,
      "size": 288165
    },
    {
      "url": "https://jefrydco.id/blog/",
      "device": "mobile",
      "perf": 0.92,
      "fid": 0,
      "lcp": 3193.03,
      "cls": 0.00158,
      "fcp": 1590.74,
      "fci": 0,
      "tbt": 0,
      "tti": 3193.03,
      "si": 2695.35,
      "req": 16,
      "size": 248201
    },
    {
      "url": "https://jefrydco.id/blog/",
      "device": "desktop",
      "perf": 1,
      "fid": 0,
      "lcp": 521,
      "cls": 0.00821,
      "fcp": 336,
      "fci": 0,
      "tbt": 44,
      "tti": 655,
      "si": 336,
      "req": 16,
      "size": 248185
    },
    {
      "url": "https://jefrydco.id/talk/",
      "device": "mobile",
      "perf": 0.83,
      "fid": 0,
      "lcp": 4502,
      "cls": 0,
      "fcp": 1611.5,
      "fci": 0,
      "tbt": 56,
      "tti": 4502,
      "si": 3447.84,
      "req": 22,
      "size": 1095444
    },
    {
      "url": "https://jefrydco.id/talk/",
      "device": "desktop",
      "perf": 0.98,
      "fid": 0,
      "lcp": 1061,
      "cls": 0.00004,
      "fcp": 321,
      "fci": 0,
      "tbt": 0,
      "tti": 1063,
      "si": 537.22,
      "req": 22,
      "size": 1095429
    }
  ]
}