{
  "timestamp": "2023-04-17T02:14:38.284Z",
  "reports": [
    {
      "url": "https://jefrydco.id/",
      "device": "mobile",
      "perf": 0.71,
      "fid": 0,
      "lcp": 3470,
      "cls": 0.01068,
      "fcp": 848,
      "fci": 0,
      "tbt": 892.5,
      "tti": 3505.5,
      "si": 1004.64,
      "req": 24,
      "size": 339699
    },
    {
      "url": "https://jefrydco.id/",
      "device": "desktop",
      "perf": 1,
      "fid": 0,
      "lcp": 794,
      "cls": 0.00139,
      "fcp": 350,
      "fci": 0,
      "tbt": 34,
      "tti": 434,
      "si": 350,
      "req": 24,
      "size": 339770
    },
    {
      "url": "https://jefrydco.id/blog/",
      "device": "mobile",
      "perf": 0.53,
      "fid": 0,
      "lcp": 5310.5,
      "cls": 0.02418,
      "fcp": 1438,
      "fci": 0,
      "tbt": 1300,
      "tti": 5091.5,
      "si": 4031.26,
      "req": 28,
      "size": 842115
    },
    {
      "url": "https://jefrydco.id/blog/",
      "device": "desktop",
      "perf": 0.97,
      "fid": 0,
      "lcp": 1288,
      "cls": 0.00084,
      "fcp": 390,
      "fci": 0,
      "tbt": 59,
      "tti": 657,
      "si": 753.23,
      "req": 29,
      "size": 866303
    },
    {
      "url": "https://jefrydco.id/talk/",
      "device": "mobile",
      "perf": 0.6,
      "fid": 0,
      "lcp": 4878,
      "cls": 0.01477,
      "fcp": 2280,
      "fci": 0,
      "tbt": 778,
      "tti": 4023,
      "si": 3370.93,
      "req": 28,
      "size": 821469
    },
    {
      "url": "https://jefrydco.id/talk/",
      "device": "desktop",
      "perf": 0.95,
      "fid": 0,
      "lcp": 1216,
      "cls": 0.00063,
      "fcp": 510,
      "fci": 0,
      "tbt": 133.5,
      "tti": 792,
      "si": 578.74,
      "req": 33,
      "size": 1090568
    }
  ]
}