{
  "timestamp": "2024-10-28T02:39:33.702Z",
  "reports": [
    {
      "url": "https://jefrydco.id/",
      "device": "mobile",
      "perf": 0.93,
      "fid": 0,
      "lcp": 820.63,
      "cls": 0.01068,
      "fcp": 820.63,
      "fci": 0,
      "tbt": 324.5,
      "tti": 3304.88,
      "si": 896.71,
      "req": 22,
      "size": 343852
    },
    {
      "url": "https://jefrydco.id/",
      "device": "desktop",
      "perf": 1,
      "fid": 0,
      "lcp": 230.1,
      "cls": 0.00138,
      "fcp": 230.1,
      "fci": 0,
      "tbt": 56,
      "tti": 491.21,
      "si": 348.21,
      "req": 22,
      "size": 343801
    },
    {
      "url": "https://jefrydco.id/blog/",
      "device": "mobile",
      "perf": 0.65,
      "fid": 0,
      "lcp": 4518.4,
      "cls": 0.02418,
      "fcp": 1861.07,
      "fci": 0,
      "tbt": 715.5,
      "tti": 4605.78,
      "si": 1941.36,
      "req": 26,
      "size": 847008
    },
    {
      "url": "https://jefrydco.id/blog/",
      "device": "desktop",
      "perf": 0.99,
      "fid": 0,
      "lcp": 1021.62,
      "cls": 0.00056,
      "fcp": 333.04,
      "fci": 0,
      "tbt": 41,
      "tti": 1041.68,
      "si": 447.51,
      "req": 27,
      "size": 871422
    },
    {
      "url": "https://jefrydco.id/talk/",
      "device": "mobile",
      "perf": 0.62,
      "fid": 0,
      "lcp": 4059.01,
      "cls": 0.01068,
      "fcp": 1204,
      "fci": 0,
      "tbt": 1366.5,
      "tti": 4088.42,
      "si": 1578.08,
      "req": 26,
      "size": 826332
    },
    {
      "url": "https://jefrydco.id/talk/",
      "device": "desktop",
      "perf": 0.97,
      "fid": 0,
      "lcp": 1096.26,
      "cls": 0.01045,
      "fcp": 361,
      "fci": 0,
      "tbt": 114,
      "tti": 1122.94,
      "si": 444.36,
      "req": 31,
      "size": 1096373
    }
  ]
}