{
  "timestamp": "2022-11-22T02:58:42.402Z",
  "reports": [
    {
      "url": "https://jefrydco.id/",
      "device": "mobile",
      "perf": 0.73,
      "fid": 0,
      "lcp": 3728,
      "cls": 0.00107,
      "fcp": 911,
      "fci": 0,
      "tbt": 579.5,
      "tti": 3803,
      "si": 1661.18,
      "req": 24,
      "size": 336898
    },
    {
      "url": "https://jefrydco.id/",
      "device": "desktop",
      "perf": 0.99,
      "fid": 3,
      "lcp": 937,
      "cls": 0.00139,
      "fcp": 254,
      "fci": 0,
      "tbt": 20,
      "tti": 654,
      "si": 421.09,
      "req": 24,
      "size": 337154
    },
    {
      "url": "https://jefrydco.id/blog/",
      "device": "mobile",
      "perf": 0.55,
      "fid": 0,
      "lcp": 5542.5,
      "cls": 0.00107,
      "fcp": 1142,
      "fci": 0,
      "tbt": 907.5,
      "tti": 5580,
      "si": 2610.95,
      "req": 27,
      "size": 726107
    },
    {
      "url": "https://jefrydco.id/blog/",
      "device": "desktop",
      "perf": 1,
      "fid": 3,
      "lcp": 409,
      "cls": 0.00054,
      "fcp": 409,
      "fci": 0,
      "tbt": 0,
      "tti": 409,
      "si": 409,
      "req": 12,
      "size": 293130
    },
    {
      "url": "https://jefrydco.id/talk/",
      "device": "mobile",
      "perf": 0.62,
      "fid": 0,
      "lcp": 5042,
      "cls": 0.00107,
      "fcp": 1115,
      "fci": 0,
      "tbt": 726,
      "tti": 3814,
      "si": 2416.81,
      "req": 27,
      "size": 527589
    },
    {
      "url": "https://jefrydco.id/talk/",
      "device": "desktop",
      "perf": 0.92,
      "fid": 3,
      "lcp": 1421,
      "cls": 0.00063,
      "fcp": 580,
      "fci": 0,
      "tbt": 157.5,
      "tti": 974,
      "si": 668.1,
      "req": 33,
      "size": 1088955
    }
  ]
}