{
  "timestamp": "2025-09-25T02:42:55.799Z",
  "reports": [
    {
      "url": "https://jefrydco.id/",
      "device": "mobile",
      "perf": 0.92,
      "fid": 0,
      "lcp": 1964.48,
      "cls": 0.01725,
      "fcp": 1964.48,
      "fci": 0,
      "tbt": 291.5,
      "tti": 3480.11,
      "si": 1964.48,
      "req": 22,
      "size": 346527
    },
    {
      "url": "https://jefrydco.id/",
      "device": "desktop",
      "perf": 1,
      "fid": 0,
      "lcp": 367.28,
      "cls": 0.00134,
      "fcp": 367.28,
      "fci": 0,
      "tbt": 21,
      "tti": 484.18,
      "si": 367.28,
      "req": 22,
      "size": 346497
    },
    {
      "url": "https://jefrydco.id/blog/",
      "device": "mobile",
      "perf": 0.83,
      "fid": 0,
      "lcp": 4624.13,
      "cls": 0.02418,
      "fcp": 1501.04,
      "fci": 0,
      "tbt": 91,
      "tti": 4706.63,
      "si": 1919.85,
      "req": 26,
      "size": 850763
    },
    {
      "url": "https://jefrydco.id/blog/",
      "device": "desktop",
      "perf": 0.99,
      "fid": 0,
      "lcp": 1034.87,
      "cls": 0.00056,
      "fcp": 455.06,
      "fci": 0,
      "tbt": 33,
      "tti": 1054.9,
      "si": 479.05,
      "req": 27,
      "size": 876402
    },
    {
      "url": "https://jefrydco.id/talk/",
      "device": "mobile",
      "perf": 0.86,
      "fid": 0,
      "lcp": 3977.01,
      "cls": 0.02133,
      "fcp": 1801,
      "fci": 0,
      "tbt": 89.5,
      "tti": 4044.61,
      "si": 1801,
      "req": 26,
      "size": 828611
    },
    {
      "url": "https://jefrydco.id/talk/",
      "device": "desktop",
      "perf": 0.98,
      "fid": 0,
      "lcp": 1097.01,
      "cls": 0.0004,
      "fcp": 374,
      "fci": 0,
      "tbt": 53,
      "tti": 1127.61,
      "si": 428.03,
      "req": 31,
      "size": 1097724
    }
  ]
}