{
  "timestamp": "2021-08-15T02:06:03.303Z",
  "reports": [
    {
      "url": "https://jefrydco.id/",
      "device": "mobile",
      "perf": 0.94,
      "fid": 0,
      "lcp": 857,
      "cls": 0.00098,
      "fcp": 840,
      "fci": 0,
      "tbt": 283.5,
      "tti": 3555,
      "si": 1542.19,
      "req": 22,
      "size": 316648
    },
    {
      "url": "https://jefrydco.id/",
      "device": "desktop",
      "perf": 1,
      "fid": 0,
      "lcp": 270,
      "cls": 0.00116,
      "fcp": 270,
      "fci": 0,
      "tbt": 0,
      "tti": 270,
      "si": 382.99,
      "req": 22,
      "size": 316629
    },
    {
      "url": "https://jefrydco.id/blog/",
      "device": "mobile",
      "perf": 0.66,
      "fid": 0,
      "lcp": 5209.5,
      "cls": 0.00098,
      "fcp": 952,
      "fci": 0,
      "tbt": 526,
      "tti": 4923.5,
      "si": 2161.61,
      "req": 25,
      "size": 705242
    },
    {
      "url": "https://jefrydco.id/blog/",
      "device": "desktop",
      "perf": 0.97,
      "fid": 0,
      "lcp": 1255.5,
      "cls": 0.0005,
      "fcp": 350,
      "fci": 0,
      "tbt": 2,
      "tti": 1147.5,
      "si": 393.99,
      "req": 27,
      "size": 842597
    }
  ]
}