{
  "timestamp": "2022-08-16T03:27:16.267Z",
  "reports": [
    {
      "url": "https://jefrydco.id/",
      "device": "mobile",
      "perf": 0.91,
      "fid": 0,
      "lcp": 3247.5,
      "cls": 0.00136,
      "fcp": 827,
      "fci": 0,
      "tbt": 147.5,
      "tti": 3397.5,
      "si": 1338.75,
      "req": 24,
      "size": 338680
    },
    {
      "url": "https://jefrydco.id/",
      "device": "desktop",
      "perf": 1,
      "fid": 0,
      "lcp": 812,
      "cls": 0.00138,
      "fcp": 244,
      "fci": 0,
      "tbt": 0,
      "tti": 244,
      "si": 331.24,
      "req": 24,
      "size": 338840
    },
    {
      "url": "https://jefrydco.id/blog/",
      "device": "mobile",
      "perf": 0.54,
      "fid": 0,
      "lcp": 5583,
      "cls": 0.00107,
      "fcp": 1051,
      "fci": 0,
      "tbt": 1047.5,
      "tti": 5719,
      "si": 2364.66,
      "req": 27,
      "size": 728169
    },
    {
      "url": "https://jefrydco.id/blog/",
      "device": "desktop",
      "perf": 0.97,
      "fid": 0,
      "lcp": 1310,
      "cls": 0.00084,
      "fcp": 311,
      "fci": 0,
      "tbt": 27,
      "tti": 1242,
      "si": 604.32,
      "req": 29,
      "size": 865595
    },
    {
      "url": "https://jefrydco.id/talk/",
      "device": "mobile",
      "perf": 0.68,
      "fid": 0,
      "lcp": 4982.5,
      "cls": 0.00107,
      "fcp": 990,
      "fci": 0,
      "tbt": 489.5,
      "tti": 3904,
      "si": 2317.53,
      "req": 27,
      "size": 529833
    },
    {
      "url": "https://jefrydco.id/talk/",
      "device": "desktop",
      "perf": 0.94,
      "fid": 0,
      "lcp": 1451,
      "cls": 0.00039,
      "fcp": 449,
      "fci": 0,
      "tbt": 118,
      "tti": 879,
      "si": 545.38,
      "req": 33,
      "size": 1091749
    }
  ]
}