{
  "timestamp": "2022-03-21T02:40:28.283Z",
  "reports": [
    {
      "url": "https://jefrydco.id/",
      "device": "mobile",
      "perf": 0.8,
      "fid": 0,
      "lcp": 3478,
      "cls": 0.00107,
      "fcp": 809,
      "fci": 0,
      "tbt": 410,
      "tti": 3628,
      "si": 1782.66,
      "req": 24,
      "size": 339008
    },
    {
      "url": "https://jefrydco.id/",
      "device": "desktop",
      "perf": 0.99,
      "fid": 0,
      "lcp": 855,
      "cls": 0.00138,
      "fcp": 235,
      "fci": 0,
      "tbt": 0,
      "tti": 239,
      "si": 461.65,
      "req": 24,
      "size": 339215
    },
    {
      "url": "https://jefrydco.id/blog/",
      "device": "mobile",
      "perf": 0.56,
      "fid": 0,
      "lcp": 5610.5,
      "cls": 0.00136,
      "fcp": 973,
      "fci": 0,
      "tbt": 888,
      "tti": 5370.5,
      "si": 2573.19,
      "req": 27,
      "size": 728501
    },
    {
      "url": "https://jefrydco.id/blog/",
      "device": "desktop",
      "perf": 0.95,
      "fid": 0,
      "lcp": 1339.5,
      "cls": 0.00084,
      "fcp": 390,
      "fci": 0,
      "tbt": 105.5,
      "tti": 1303,
      "si": 674.09,
      "req": 29,
      "size": 865896
    },
    {
      "url": "https://jefrydco.id/talk/",
      "device": "mobile",
      "perf": 0.61,
      "fid": 0,
      "lcp": 5026.5,
      "cls": 0.00107,
      "fcp": 961,
      "fci": 0,
      "tbt": 798.5,
      "tti": 4067,
      "si": 2119.42,
      "req": 27,
      "size": 530090
    },
    {
      "url": "https://jefrydco.id/talk/",
      "device": "desktop",
      "perf": 0.93,
      "fid": 0,
      "lcp": 1471,
      "cls": 0.00039,
      "fcp": 430,
      "fci": 0,
      "tbt": 140,
      "tti": 920,
      "si": 710,
      "req": 33,
      "size": 1091976
    }
  ]
}