{
  "timestamp": "2024-08-13T02:23:30.437Z",
  "reports": [
    {
      "url": "https://jefrydco.id/",
      "device": "mobile",
      "perf": 0.83,
      "fid": 0,
      "lcp": 3291.09,
      "cls": 0.01068,
      "fcp": 836.5,
      "fci": 0,
      "tbt": 411.5,
      "tti": 3321.68,
      "si": 836.5,
      "req": 22,
      "size": 339027
    },
    {
      "url": "https://jefrydco.id/",
      "device": "desktop",
      "perf": 1,
      "fid": 0,
      "lcp": 752.9,
      "cls": 0.00139,
      "fcp": 216.9,
      "fci": 0,
      "tbt": 4,
      "tti": 382.8,
      "si": 233.55,
      "req": 22,
      "size": 339237
    },
    {
      "url": "https://jefrydco.id/blog/",
      "device": "mobile",
      "perf": 0.62,
      "fid": 0,
      "lcp": 4694.13,
      "cls": 0.02418,
      "fcp": 1883.06,
      "fci": 0,
      "tbt": 868.51,
      "tti": 4732.6,
      "si": 1883.06,
      "req": 26,
      "size": 841456
    },
    {
      "url": "https://jefrydco.id/blog/",
      "device": "desktop",
      "perf": 0.98,
      "fid": 0,
      "lcp": 1062.09,
      "cls": 0.00056,
      "fcp": 454.04,
      "fci": 0,
      "tbt": 51,
      "tti": 711.05,
      "si": 540.99,
      "req": 27,
      "size": 865427
    },
    {
      "url": "https://jefrydco.id/talk/",
      "device": "mobile",
      "perf": 0.7,
      "fid": 0,
      "lcp": 4029.76,
      "cls": 0.01477,
      "fcp": 1021,
      "fci": 0,
      "tbt": 676.5,
      "tti": 3572.61,
      "si": 1682.97,
      "req": 26,
      "size": 820515
    },
    {
      "url": "https://jefrydco.id/talk/",
      "device": "desktop",
      "perf": 0.98,
      "fid": 0,
      "lcp": 1086.03,
      "cls": 0.00044,
      "fcp": 332,
      "fci": 0,
      "tbt": 87,
      "tti": 708.1,
      "si": 463.47,
      "req": 31,
      "size": 1089471
    }
  ]
}