{
  "timestamp": "2023-12-01T02:13:02.263Z",
  "reports": [
    {
      "url": "https://jefrydco.id/",
      "device": "mobile",
      "perf": 0.77,
      "fid": 0,
      "lcp": 3401,
      "cls": 0.01068,
      "fcp": 925.5,
      "fci": 0,
      "tbt": 586,
      "tti": 3512,
      "si": 925.5,
      "req": 0,
      "size": 0
    },
    {
      "url": "https://jefrydco.id/",
      "device": "desktop",
      "perf": 0.99,
      "fid": 0,
      "lcp": 893.5,
      "cls": 0.00139,
      "fcp": 352,
      "fci": 0,
      "tbt": 2,
      "tti": 576.5,
      "si": 352,
      "req": 0,
      "size": 0
    },
    {
      "url": "https://jefrydco.id/blog/",
      "device": "mobile",
      "perf": 0.56,
      "fid": 0,
      "lcp": 5405.5,
      "cls": 0.02418,
      "fcp": 1124,
      "fci": 0,
      "tbt": 1238.5,
      "tti": 5217.5,
      "si": 2040.99,
      "req": 0,
      "size": 0
    },
    {
      "url": "https://jefrydco.id/blog/",
      "device": "desktop",
      "perf": 0.95,
      "fid": 0,
      "lcp": 1333,
      "cls": 0.00054,
      "fcp": 359,
      "fci": 0,
      "tbt": 110.5,
      "tti": 1159,
      "si": 592.78,
      "req": 0,
      "size": 0
    },
    {
      "url": "https://jefrydco.id/talk/",
      "device": "mobile",
      "perf": 0.61,
      "fid": 0,
      "lcp": 4768,
      "cls": 0.01477,
      "fcp": 1118,
      "fci": 0,
      "tbt": 961,
      "tti": 3806.25,
      "si": 2045.64,
      "req": 0,
      "size": 0
    },
    {
      "url": "https://jefrydco.id/talk/",
      "device": "desktop",
      "perf": 0.92,
      "fid": 0,
      "lcp": 1375.5,
      "cls": 0.00039,
      "fcp": 350.5,
      "fci": 0,
      "tbt": 168,
      "tti": 801,
      "si": 653.74,
      "req": 0,
      "size": 0
    }
  ]
}